map_location/__init__.py
map_location/apps.py
map_location/fields.py
map_location/static/map-location.js
map_location/static/leaflet/.DS_Store
map_location/static/leaflet/leaflet.css
map_location/static/leaflet/leaflet.js
map_location/static/leaflet/leaflet.js.map
map_location/static/leaflet/images/layers-2x.png
map_location/static/leaflet/images/layers.png
map_location/static/leaflet/images/marker-icon-2x.png
map_location/static/leaflet/images/marker-icon.png
map_location/static/leaflet/images/marker-shadow.png
map_location/static/leaflet/locate/.DS_Store
map_location/static/leaflet/locate/L.Control.Locate.css
map_location/static/leaflet/locate/L.Control.Locate.min.js
map_location/static/leaflet/locate/L.Control.Locate.min.js.map
map_location/templates/forms/map-location.html
django_map_location-0.9.2.dist-info/LICENSE
django_map_location-0.9.2.dist-info/METADATA
django_map_location-0.9.2.dist-info/WHEEL
django_map_location-0.9.2.dist-info/top_level.txt
django_map_location-0.9.2.dist-info/RECORD
