Metadata-Version: 2.1
Name: django-map-location
Version: 0.9.2
Summary: Django Map-Location Field
Home-page: https://github.com/relikd/django-map-location
Author: relikd
License: MIT
Keywords: OpenStreetMap,OSM,Leaflet,Django,Geo,GPS,Position,Location
Platform: UNKNOWN
Classifier: Development Status :: 4 - Beta
Classifier: Environment :: Web Environment
Classifier: Framework :: Django
Classifier: Framework :: Django :: 4.0
Classifier: Intended Audience :: Developers
Classifier: License :: OSI Approved :: MIT License
Classifier: Operating System :: OS Independent
Classifier: Programming Language :: Python :: 3.6
Classifier: Programming Language :: Python :: 3.7
Classifier: Programming Language :: Python :: 3.8
Requires-Python: >=3.6
Requires-Dist: Django (>=4.0)
